{"is_source_file": true, "format": "SQL", "description": "This file contains SQL seed data scripts for initializing the database with development data, including sample users, profiles, courses, lessons, enrollments, posts, and analytics events.", "external_files": [], "external_methods": [], "published": [], "classes": [], "methods": [], "calls": [], "search-terms": ["seed.sql", "database initialization", "seed data", "SQL inserts", "development data"], "state": 2, "file_id": 72, "knowledge_revision": 183, "git_revision": "", "hash": "d2671980465f4abb1e1ff8e7a3df0383", "format-version": 4, "code-base-name": "learning_platform_frontend", "filename": "db/seed.sql", "revision_history": [{"183": ""}]}