{"is_source_file": false, "format": null, "description": null, "external_files": [], "external_methods": [], "published": [], "classes": [], "methods": [], "calls": [], "search-terms": [], "state": 2, "file_id": 215, "knowledge_revision": 667, "git_revision": "9853817db5e2ae2e1a82b7b28c5f807e745345cd", "hash": "1afffda70ec424290736d49815dfd94a", "format-version": 4, "code-base-name": "learning_platform_frontend", "filename": "learning_platform_frontend/src/services/README.examples.md", "revision_history": [{"667": "9853817db5e2ae2e1a82b7b28c5f807e745345cd"}]}